{
  "onset": {
    "Description": "Event onset",
    "Units": "second"
  },
  "response_time": {
    "Description": "Latency of button press after auditory stimulus",
    "Levels": {
      "Units": "millisecond"
    }
  },
  "trial_type": {
    "Description": "Type of event",
    "Levels": {
      "stimulus": "Auditory stimulus",
      "responses": "Behavioral response"
    }
  },
  "value": {
    "Description": "Value of event",
    "Levels": {
      "response": "Response of the subject",
      "standard": "Standard at 500 hz for 60 ms",
      "ignore": "Ignore - not a real event",
      "oddball": "Oddball at 1000 hz for 60 ms",
      "noise": "White noise for 60 ms"
    }
  }
}